odoo10_addon_sale_stock_operating_unit-10.0.1.0.0-py2.7-nspkg.pth
odoo10_addon_sale_stock_operating_unit-10.0.1.0.0.dist-info/top_level.txt
odoo10_addon_sale_stock_operating_unit-10.0.1.0.0.dist-info/WHEEL
odoo10_addon_sale_stock_operating_unit-10.0.1.0.0.dist-info/RECORD
odoo10_addon_sale_stock_operating_unit-10.0.1.0.0.dist-info/metadata.json
odoo10_addon_sale_stock_operating_unit-10.0.1.0.0.dist-info/DESCRIPTION.rst
odoo10_addon_sale_stock_operating_unit-10.0.1.0.0.dist-info/METADATA
odoo10_addon_sale_stock_operating_unit-10.0.1.0.0.dist-info/namespace_packages.txt
odoo/addons/sale_stock_operating_unit/__manifest__.py
odoo/addons/sale_stock_operating_unit/__init__.py
odoo/addons/sale_stock_operating_unit/README.rst
odoo/addons/sale_stock_operating_unit/models/stock_move.py
odoo/addons/sale_stock_operating_unit/models/sale_order.py
odoo/addons/sale_stock_operating_unit/models/stock_warehouse.py
odoo/addons/sale_stock_operating_unit/models/__init__.py
odoo/addons/sale_stock_operating_unit/tests/__init__.py
odoo/addons/sale_stock_operating_unit/tests/test_sale_stock_operating_unit.py
odoo/addons/sale_stock_operating_unit/static/description/icon.png
